houseplant/__init__.py
houseplant/__version__.py
houseplant/cli.py
houseplant/clickhouse_client.py
houseplant/houseplant.py
houseplant/utils.py
houseplant-0.2.5.dist-info/AUTHORS.rst
houseplant-0.2.5.dist-info/LICENSE
houseplant-0.2.5.dist-info/METADATA
houseplant-0.2.5.dist-info/WHEEL
houseplant-0.2.5.dist-info/entry_points.txt
houseplant-0.2.5.dist-info/top_level.txt
houseplant-0.2.5.dist-info/RECORD
