Metadata-Version: 2.2
Name: houseplant
Version: 0.2.5
Summary: Database Migrations for ClickHouse.
Author-email: June <eng@june.so>
Maintainer-email: June <eng@june.so>
License: MIT license
Project-URL: Homepage, https://github.com/juneHQ/houseplant
Project-URL: Changelog, https://github.com/juneHQ/houseplant/releases
Project-URL: Issues, https://github.com/juneHQ/houseplant/issues
Project-URL: CI, https://github.com/juneHQ/houseplant/actions
Classifier: License :: OSI Approved :: MIT License
Classifier: Topic :: Database
Classifier: Programming Language :: Python :: 3.10
Classifier: Programming Language :: Python :: 3.11
Classifier: Programming Language :: Python :: 3.12
Classifier: Programming Language :: Python :: 3.13
License-File: LICENSE
License-File: AUTHORS.rst
Requires-Dist: clickhouse-driver<0.3,>=0.2.9
Requires-Dist: pyyaml<6.1,>=6.0.2
Requires-Dist: typer<0.15,>=0.14.0
Requires-Dist: python-dotenv<1.1,>=1.0.1
Provides-Extra: dev
Requires-Dist: ruff==0.8.6; extra == "dev"
Requires-Dist: pytest==8.3.4; extra == "dev"
Requires-Dist: pytest-cov==6.0.0; extra == "dev"
Requires-Dist: pytest-mock==3.14.0; extra == "dev"
Requires-Dist: sphinx; extra == "dev"
Requires-Dist: tomli; extra == "dev"
